{
  "id": "随笔/img_pkg-sv",
  "title": "img_pkg-sv",
  "description": "",
  "source": "@site/docs/随笔/img_pkg-sv.md",
  "sourceDirName": "随笔",
  "slug": "/随笔/img_pkg-sv",
  "permalink": "/docs/随笔/img_pkg-sv",
  "draft": false,
  "unlisted": false,
  "editUrl": "https://github.com/facebook/docusaurus/tree/main/packages/create-docusaurus/templates/shared/docs/随笔/img_pkg-sv.md",
  "tags": [],
  "version": "current",
  "frontMatter": {},
  "sidebar": "tutorialSidebar",
  "previous": {
    "title": "img_monitor-sv",
    "permalink": "/docs/随笔/img_monitor-sv"
  },
  "next": {
    "title": "img_scoreboard-sv",
    "permalink": "/docs/随笔/img_scoreboard-sv"
  }
}